<?xml version="1.0" encoding="utf-8"?>
<Layouts>
  <Layout layout_name="settings_layout_RuntimeFeedGadget" layout_id="runtime" layout_guid="77956c44-2b7c-4cbb-9104-68fe278023df">
    <Grid stylename="grid_container" height="24dpi_px" width="600dpi_px" left="0dpi_px" top="0dpi_px" grid_columnlayout="['100dpi_px', '1*', '120dpi_px']" row_spacing="6dpi_px" column_spacing="6dpi_px" grid_resize="ResizeGrid">
      <Cell row="0" column="0" flow_index="0">
        <ChildGadgets>
          <TextBox stylename="text_box" layout_id="name" layout_guid="9675a2bb-d566-4b0d-ac3a-f0ea9d2e206b" left="0dpi_px" top="0dpi_px" />
        </ChildGadgets>
      </Cell>
      <Cell row="0" column="1" flow_index="0">
        <ChildGadgets>
          <TextBox stylename="text_box" layout_id="url" layout_guid="c0d972bc-9ab9-4c30-bdcc-6a0a20b28060" left="0dpi_px" top="0dpi_px" />
        </ChildGadgets>
      </Cell>
      <Cell row="0" column="2" flow_index="0">
        <ChildGadgets>
          <Button stylename="button_up" layout_id="delete" layout_guid="6fe9fda2-60b4-4a3b-9e37-645f65bcc300" height="24px" width="100dpi_px" top="0dpi_px" localise_name="Button_Delete" />
        </ChildGadgets>
      </Cell>
    </Grid>
  </Layout>
  <Layout layout_name="settings_layout_runtimer_gadget" layout_guid="4b09adf5-fb13-4e34-8515-34f6bd927eab">
    <Gadgets>
      <TextBox stylename="text_box" layout_id="setting_value" layout_guid="10774180-3be4-4125-bd36-6b99a29769e3" width="200dpi_px" left="0dpi_px" margin_right="10dpi_px" />
      <Label stylename="settings_gadget_label" layout_id="setting_label" layout_guid="1b755df1-29f7-4068-b06d-14355f5646e1" height="16dpi_px" width="0dpi_px" left="215dpi_px" margin_left="5dpi_px" />
    </Gadgets>
  </Layout>
  <Layout layout_name="settings_layout_multi_image" layout_guid="be5cd5d4-c8be-42ac-8314-e382a0ac9094">
    <ChildGadgets>
      <StackPanel stylename="settings_gadget_stack_panel_vertical" stack_order="TopToBottom">
        <ChildGadgets>
          <Label stylename="label" layout_id="setting_label" layout_guid="94b6449d-63fd-43b8-817c-35340fc9ecd1" height="16dpi_px" width="0dpi_px" left="0dpi_px" />
          <Grid stylename="multi_image_grid" layout_id="imagegrid" layout_guid="822a9e03-4744-4869-8e5e-71e7c883c522" grid_columnlayout="['*', '*', '*']" />
        </ChildGadgets>
      </StackPanel>
    </ChildGadgets>
  </Layout>
  <Layout layout_name="settings_layout_path_with_check" layout_guid="e36e9384-149a-34cc-85f9-1b71bb07d2a5">
    <Gadgets>
      <StackPanel stylename="settings_gadget_stack_panel_vertical">
        <ChildGadgets>
          <Label stylename="settings_gadget_label" layout_id="setting_label" height="16dpi_px" />
          <Label stylename="settings_gadget_label" caption="Not Checked" layout_id="checking_label" />
        </ChildGadgets>
      </StackPanel>
      <TextBox stylename="settings_textbox_style" layout_id="setting_value" margin_left="10dpi_px" margin_right="10dpi_px" />
      <Button stylename="settings_browse_button" layout_id="setting_button" layout_guid="f07a3e3e-9a05-4d67-a3b8-6bbd1d6478c4" height="24px" left="0dpi_px" />
    </Gadgets>
  </Layout>
  <Layout layout_name="settings_layout_text_filename" layout_guid="bc51cebd-37e5-40e6-bfd6-e2e959507476">
    <Grid stylename="grid_container" height="20dpi_px" width="100%" grid_rowlayout="['auto']" grid_columnlayout="['auto', 'auto', 'auto']" column_spacing="10dpi_px" grid_resize="ResizeGrid">
      <Cell row="0" column="0" flow_index="0">
        <ChildGadgets>
          <TextBox stylename="basic_text_box" layout_id="setting_value" layout_guid="1eefef00-1371-4d39-aedc-65e95457503d" width="350dpi_px" left="0dpi_px" />
        </ChildGadgets>
      </Cell>
      <Cell row="0" column="1" flow_index="0">
        <Gadgets>
          <Button stylename="settings_browse_button" layout_id="setting_button" layout_guid="f07a3e3e-9a05-4d67-a3b8-6bbd1d6478c4" height="24px" left="0dpi_px" />
        </Gadgets>
      </Cell>
      <Cell row="0" column="2" flow_index="0">
        <Gadgets>
          <Label stylename="settings_gadget_label" layout_id="setting_label" layout_guid="3147f025-7b11-4479-9b54-1066b84a6871" height="16px" width="27px" margin_left="5dpi_px" caption="hello" />
        </Gadgets>
      </Cell>
    </Grid>
  </Layout>
  <Layout layout_name="settings_layout_switch_authoring_editor_invalid_platform" layout_guid="1eaa1650-6fba-4a8e-a55b-5774c23ac2aa">
    <Cell row="0" column="0" flow_index="0">
      <ChildGadgets>
      </ChildGadgets>
    </Cell>
    <Cell row="1" column="0" flow_index="0">
      <ChildGadgets>
        <Label stylename="label" height="16px" width="298px" localise_caption="switch_tools_invalid_platform" />
      </ChildGadgets>
    </Cell>
  </Layout>
  <Layout layout_name="settings_layout_switch_authoring_editor" layout_guid="1eaa1650-6fba-4a8e-a55b-5774c23ac2aa">
    <!--<Grid stylename="grid_container" grid_rowlayout="['auto', 'auto']" grid_columnlayout="['600dpi_px']" row_spacing="6dpi_px" grid_resize="ResizeGrid">-->
    <Cell row="0" column="0" flow_index="0">
      <ChildGadgets>
      </ChildGadgets>
    </Cell>
    <Cell row="1" column="0" flow_index="0">
      <ChildGadgets>
        <Button stylename="button_up" layout_id="open" layout_guid="284311f8-e143-4afd-aee1-0da01b4b9223" height="24px" localise_name="preferences_open_authoring" />
      </ChildGadgets>
    </Cell>
    <!--</Grid>-->
  </Layout>
  <Layout layout_name="settings_layout_switch_patch_maker_invalid_platform" layout_guid="1eaa1650-6fba-4a8e-a55b-5774c23ac2aa">
    <Cell row="0" column="0" flow_index="0">
      <ChildGadgets>
        <Label stylename="label" height="16px" width="298px" localise_caption="switch_tools_invalid_platform" />
      </ChildGadgets>
    </Cell>
  </Layout>
  <Layout layout_name="settings_layout_switch_patch_maker" layout_guid="1eaa1650-6fba-4a8e-a55b-5774c23ac2ab">
    <!--<Grid stylename="grid_container" grid_rowlayout="['auto', 'auto', 'auto']" grid_columnlayout="['600dpi_px', '1*']" row_spacing="6dpi_px" grid_resize="ResizeGrid">-->
      <Cell row="0" column="0" flow_index="0">
        <ChildGadgets>
          <Label stylename="label" height="16px" width="298px" localise_caption="preferences_patch_original_package" />
        </ChildGadgets>
      </Cell>
      <Cell row="0" column="1" flow_index="0">
        <ChildGadgets>
          <FileInputGadget stylename="file_input" layout_id="original" layout_guid="e14c03d4-da4b-4927-80b8-c16a94248a0e" />
        </ChildGadgets>
      </Cell>
    <Cell row="1" column="0" flow_index="0">
      <ChildGadgets>
        <Label stylename="label" height="16px" width="288px" localise_caption="preferences_patch_current_package" />
      </ChildGadgets>
    </Cell>
    <Cell row="1" column="1" flow_index="0">
      <ChildGadgets>
        <FileInputGadget stylename="file_input" layout_id="current" layout_guid="e14c03d4-da4b-4927-80b8-c16a94248a0a" />
      </ChildGadgets>
    </Cell>
      <Cell row="2" column="0" flow_index="0">
        <ChildGadgets>
          <Label stylename="label" height="16px" width="288px" localise_caption="preferences_patch_previous_patch" />
        </ChildGadgets>
      </Cell>
      <Cell row="2" column="1" flow_index="0">
        <ChildGadgets>
          <FileInputGadget stylename="file_input" layout_id="previous" layout_guid="e14c03d4-da4b-4927-80b8-c16a94248a0f" />
        </ChildGadgets>
      </Cell>
      <Cell row="3" column="1" flow_index="0">
        <ChildGadgets>
          <Button stylename="button_up" layout_id="generate_patch" layout_guid="284311f8-e143-4afd-aee1-0da01b4b922a" height="24px" localise_name="preferences_generate_patch" />
        </ChildGadgets>
      </Cell>
    <Cell row="5" column="0" flow_index="0">
      <ChildGadgets>
        <Label stylename="label" height="16px" width="288px" localise_caption="preferences_patch_package" />
      </ChildGadgets>
    </Cell>
    <Cell row="5" column="1" flow_index="0">
      <ChildGadgets>
        <FileInputGadget stylename="file_input" layout_id="patch" layout_guid="e14c03d4-da4b-4927-80b8-c16a94248a01" />
      </ChildGadgets>
    </Cell>
    <Cell row="6" column="1" flow_index="0">
      <ChildGadgets>
        <Button stylename="button_up" layout_id="install_patch" layout_guid="284311f8-e143-4afd-aee1-0da01b4b9222" height="24px" localise_name="preferences_install_patch" />
      </ChildGadgets>
    </Cell>
    <!--</Grid>-->
  </Layout>
  <Layout layout_name="settings_layout_texture_page" layout_guid="e36e9384-149a-34cc-85f9-590e7f94d2a5">
    <Gadgets>
      <Label stylename="settings_gadget_label" layout_id="setting_label" height="16dpi_px" width="61dpi_px" localise_caption="Option_Texture_Page_Size" />
      <ComboBox stylename="combobox_panel" layout_id="setting_value" width="320dpi_px" left="120dpi_px">
        <ListBoxItems />
      </ComboBox>
      <Button stylename="button_up" layout_id="preview_button" layout_guid="f97d41d4-964d-4d5b-7777-b5ca67d4eda7" height="24dpi_px" width="100dpi_px" left="315dpi_px" margin_left="5dpi_px" margin_right="5dpi_px" localise_name="Button_Preview" />
    </Gadgets>
  </Layout>
  <Layout layout_name="settings_layout_text_email" layout_guid="390ce7a5-46b3-4272-9469-51c849657bab">
    <StackPanel stylename="settings_gadget_stack_panel">
      <Gadgets>
        <TextBox stylename="text_box" layout_id="setting_value" layout_guid="53f9db98-c5ac-4b5d-9c91-b8e8f91041a0" width="200dpi_px" left="0dpi_px" margin_right="10dpi_px" />
        <Label stylename="settings_gadget_label" layout_id="setting_label" layout_guid="93f7698d-e05d-4457-881d-64408b6762f5" height="16dpi_px" width="0dpi_px" left="215dpi_px" margin_left="5dpi_px" />
      </Gadgets>
    </StackPanel>
  </Layout>
  <Layout layout_name="settings_layout_font" layout_guid="e36eec75-149a-49cc-85f9-590e7f94d2a5">
    <StackPanel stylename="settings_gadget_stack_panel" height="30dpi_px" margin_left="10dpi_px" margin_right="10dpi_px" margin_top="0dpi_px" margin_bottom="10dpi_px" stack_resize="ResizeWidth">
      <Gadgets>
        <Label stylename="settings_gadget_label" layout_id="setting_label" height="16dpi_px" width="61dpi_px" caption="Font Name" />
        <ComboBox stylename="combobox_panel" layout_id="setting_value" width="320dpi_px" left="120dpi_px" top="0dpi_px">
          <ListBoxItems />
        </ComboBox>
      </Gadgets>
    </StackPanel>
  </Layout>
  <Layout layout_name="settings_layout_text_float" layout_guid="8346fb6e-96e2-4c00-a4f4-ccef92c4175a">
    <StackPanel stylename="settings_gadget_stack_panel">
      <Gadgets>
        <NumericTextBox layout_id="setting_value" layout_guid="d0cd335b-104f-4bae-b3b5-f248cc3266a7" width="100dpi_px" left="0dpi_px" margin_right="10dpi_px" input_type="Real" />
        <Label stylename="settings_gadget_label" layout_id="setting_label" layout_guid="2a9ff1ca-eb76-4c0f-a12c-d1cca1b26181" height="16dpi_px" width="0dpi_px" left="115dpi_px" margin_left="5dpi_px" />
      </Gadgets>
    </StackPanel>
  </Layout>
  <Layout layout_name="settings_layout_last_changed" layout_guid="e36e9384-4242-34cc-85f9-590e7f94d2a5">
    <Gadgets>
      <TextBox stylename="settings_textbox_style" layout_id="setting_value" margin_right="10dpi_px" />
      <Label stylename="settings_gadget_label" layout_id="setting_label" margin_left="5dpi_px" height="16dpi_px" localise_caption="Option_Project_Last_Changed" />
    </Gadgets>
  </Layout>
  <Layout layout_name="settings_layout_runtime_selection" layout_guid="f9cb770b-fd55-40ac-b438-ad523a833ec3">
    <!--<Grid stylename="runtime_selection_style" grid_rowlayout="['auto', 'auto', '1*']">-->
      <Cell row="0" column="0" flow_index="0">
        <ChildGadgets>
          <Grid stylename="grid_container" height="76dpi_px" grid_rowlayout="['auto', 'auto', 'auto', 'auto']" grid_columnlayout="['1*', '1*']" row_spacing="3dpi_px" grid_resize="ResizeGrid">
            <Cell row="0" column="0" flow_index="0">
              <ChildGadgets>
                <Label stylename="label" height="16px" width="91px" left="6dpi_px" localise_caption="runtime_current_version" />
              </ChildGadgets>
            </Cell>
            <Cell row="0" column="1" flow_index="0">
              <ChildGadgets>
                <Label stylename="label" layout_id="current_version" layout_guid="37229b56-8ed2-4261-9238-07ce103501fa" height="16px" width="0px" left="0dpi_px" />
              </ChildGadgets>
            </Cell>
            <Cell row="1" column="0" flow_index="0">
              <ChildGadgets>
                <Label stylename="label" height="16px" width="30px" left="6dpi_px" localise_caption="runtime_current_date" />
              </ChildGadgets>
            </Cell>
            <Cell row="1" column="1" flow_index="0">
              <ChildGadgets>
                <Label stylename="label" layout_id="current_date" layout_guid="6a06d068-8c7f-44d8-866b-f3ab37138fe3" height="16px" width="0px" left="0dpi_px" />
              </ChildGadgets>
            </Cell>
            <Cell row="2" column="0" flow_index="0">
              <ChildGadgets>
                <Label stylename="label" height="16px" width="50px" left="6dpi_px" localise_caption="runtime_current_location" />
              </ChildGadgets>
            </Cell>
            <Cell row="2" column="1" flow_index="0">
              <ChildGadgets>
                <Label stylename="label" layout_id="current_location" layout_guid="8b45f77e-8db7-46c9-92dc-f190a00d035e" height="16px" left="0dpi_px" auto_size="False" auto_ellipsis="True" />
              </ChildGadgets>
            </Cell>
            <Cell row="3" column="0" flow_index="0">
              <ChildGadgets>
                <CheckBox stylename="checkbox_stack" layout_id="clean_old_runtimes" layout_guid="d1234d45-9b21-4ee5-ad88-c011b1131faa" left="5dpi_px" localise_name="runtime_delete_old" />
              </ChildGadgets>
            </Cell>
            <Cell row="3" column="1" flow_index="0">
              <ChildGadgets>
                <Button stylename="button_up" layout_id="clean_now" layout_guid="5d676062-b072-492d-bbf2-5a3605194ad6" width="200dpi_px" right="6dpi_px" localise_name="clean_runtimes_now" />
              </ChildGadgets>
            </Cell>
          </Grid>
        </ChildGadgets>
      </Cell>
      <Cell row="1" column="0" flow_index="0">
        <ChildGadgets>
          <Grid stylename="grid_container" left="0dpi_px" top="22px" margin_left="0dpi_px" margin_top="22dpi_px" grid_rowlayout="['24dpi_px']" grid_columnlayout="['1*', '1*']" grid_resize="ResizeGrid">
            <Cell row="0" column="0" flow_index="0">
              <ChildGadgets>
                <StackPanel stylename="stack_panel" left="0dpi_px">
                  <ChildGadgets>
                    <Label stylename="label" height="16px" width="109px" left="6px" margin_left="6dpi_px" margin_right="6dpi_px" localise_caption="runtimes_available" />
                    <Label stylename="label" layout_id="channel_label" layout_guid="e5ac0dbc-c736-43d9-b5d6-6ff1711f9cef" height="16px" width="93px" left="121px" caption="Space Channel 9" />
                  </ChildGadgets>
                </StackPanel>
              </ChildGadgets>
            </Cell>
            <Cell row="0" column="1" flow_index="0">
              <ChildGadgets>
                <Button stylename="soundeditor_button_up" layout_id="runtime_refresh" layout_guid="c011b2ef-b2bc-46e4-aa19-202655b0bf8a" width="24dpi_px" right="47dpi_px" button_down_style="soundeditor_button_down" button_over_style="soundeditor_button_over" icon_flags="Stretch, Centre, KeepAspectRatio" icon="Runtime\icon_IDE_refresh.png" />
              </ChildGadgets>
            </Cell>
          </Grid>
        </ChildGadgets>
      </Cell>
      <Cell row="2" column="0" flow_index="0">
        <ChildGadgets>
          <Grid stylename="grid_container" grid_rowlayout="['auto', '1*']">
            <Cell row="0" column="0" flow_index="0">
              <ChildGadgets>
                <Grid stylename="grid_container" layout_id="headings" layout_guid="3afd6084-00cb-4621-aff6-62db1d7a9921" height="24dpi_px" left="0dpi_px" top="0px" grid_rowlayout="['24dpi_px']" grid_columnlayout="['0.3*', '0.2*', '1*', '0.2*']">
                  <Cell row="0" column="0" flow_index="0">
                    <ChildGadgets>
                      <Grid stylename="grid_container" grid_columnlayout="['1*', 'auto']">
                        <Cell row="0" column="0" flow_index="0">
                          <ChildGadgets>
                            <Label stylename="label" height="16px" width="64px" left="6dpi_px" localise_caption="runtime_version" />
                          </ChildGadgets>
                        </Cell>
                        <Cell row="0" column="1" flow_index="0">
                          <ChildGadgets>
                            <Button stylename="button_up" layout_id="sortby_version" layout_guid="fb9ecf15-5d95-4c65-bf7f-d04f2e4dee70" height="16dpi_px" width="16dpi_px" margin_right="3dpi_px" icon_flags="Centre, KeepAspectRatio, Downscale" icon="ArrowDown.png" />
                          </ChildGadgets>
                        </Cell>
                      </Grid>
                    </ChildGadgets>
                  </Cell>
                  <Cell row="0" column="1" flow_index="0">
                    <ChildGadgets>
                      <Grid stylename="grid_container" grid_columnlayout="['1*', 'auto']">
                        <Cell row="0" column="0" flow_index="0">
                          <ChildGadgets>
                            <Label stylename="label" height="16px" width="27px" left="6dpi_px" localise_caption="runtime_published" />
                          </ChildGadgets>
                        </Cell>
                        <Cell row="0" column="1" flow_index="0">
                          <ChildGadgets>
                            <Button stylename="button_up" layout_id="sortby_date" layout_guid="2adc08e2-a46c-4675-aa2b-5ac0db1c6a59" height="16dpi_px" width="16dpi_px" margin_right="3dpi_px" icon_flags="Centre, KeepAspectRatio, Downscale" icon="ArrowDown.png" />
                          </ChildGadgets>
                        </Cell>
                      </Grid>
                    </ChildGadgets>
                  </Cell>
                  <Cell row="0" column="2" flow_index="0">
                    <ChildGadgets>
                      <Grid stylename="grid_container" grid_columnlayout="['1*', 'auto']">
                        <Cell row="0" column="0" flow_index="0">
                          <ChildGadgets>
                            <Label stylename="label" height="16px" width="47px" left="6dpi_px" localise_caption="runtime_location" />
                          </ChildGadgets>
                        </Cell>
                        <Cell row="0" column="1" flow_index="0">
                          <ChildGadgets>
                            <Button stylename="button_up" layout_id="sortby_location" layout_guid="711047c2-023e-4eab-b8c6-c75335817c46" height="16dpi_px" width="16dpi_px" margin_right="3dpi_px" icon_flags="Centre, KeepAspectRatio, Downscale" icon="ArrowDown.png" />
                          </ChildGadgets>
                        </Cell>
                      </Grid>
                    </ChildGadgets>
                  </Cell>
                  <Cell row="0" column="3" flow_index="0">
                    <ChildGadgets>
                      <Grid stylename="grid_container" grid_columnlayout="['1*', 'auto', '0dpi_px']" grid_resize="None">
                        <Cell row="0" column="0" flow_index="0">
                          <ChildGadgets>
                            <Label stylename="label" height="16px" width="35px" localise_caption="runtime_status" />
                          </ChildGadgets>
                        </Cell>
                        <Cell row="0" column="1" flow_index="0">
                          <ChildGadgets>
                            <Button stylename="button_up" layout_id="sortby_status" layout_guid="6d5f86a1-e8b7-4a60-b5d5-382b93fa61d9" height="16dpi_px" width="16dpi_px" margin_right="3dpi_px" icon_flags="Centre, KeepAspectRatio, Downscale" icon="ArrowDown.png" />
                          </ChildGadgets>
                        </Cell>
                      </Grid>
                    </ChildGadgets>
                  </Cell>
                </Grid>
              </ChildGadgets>
            </Cell>
            <Cell row="1" column="0" flow_index="0">
              <ChildGadgets>
                <ScrollPanel stylename="default_scrollpanel" layout_id="scrollpanel" layout_guid="cd4e559f-af6e-45cb-bb26-b6a251a76504" left="0dpi_px" top="0px" scrollpanel_flags="VerticalScroll, AdjustToScrollBars">
                  <ChildGadgets>
                    <Grid stylename="grid_container" layout_id="runtime_grid" layout_guid="71beb7dd-6aa9-4aff-8da5-2537b2df86a7" left="0dpi_px" top="0dpi_px" grid_columnlayout="['0.3*', '0.2*', '1*', '0.2*']" grid_resize="ResizeGrid"></Grid>
                  </ChildGadgets>
                </ScrollPanel>
              </ChildGadgets>
            </Cell>
          </Grid>
        </ChildGadgets>
      </Cell>
    <!--</Grid>-->
  </Layout>
  <Layout layout_name="settings_layout_manual_language_selection" layout_guid="86b7006e-947b-45cf-9903-a6ee4d63c86d">
    <!--<StackPanel stylename="settings_gadget_stack_panel">-->
    <ChildGadgets>
      <ComboBox stylename="combobox_panel" layout_id="setting_value" layout_guid="aa17cd13-b2da-4e60-963a-abcef2b45c66" width="320dpi_px" left="0px" margin_right="5dpi_px">
        <ListBoxItems />
      </ComboBox>
      <Label stylename="label" layout_id="setting_label" layout_guid="ebedfb3e-4cd7-4301-89c1-5fd25cef575e" height="16px" width="253px" left="315px" margin_left="5dpi_px" localise_caption="Manual_Language_Selection" />
    </ChildGadgets>
    <!--</StackPanel>-->
  </Layout>
  <Layout layout_name="gameoptions_addon_gadget" layout_guid="955881c3-b893-4de6-aa31-a891cdb5a97b">
    <!--<ScrollPanel stylename="default_scrollpanel" height="92dpi_px" left="0px" top="0px" scrollpanel_flags="None">-->
      <ChildGadgets>
        <ScrollPanel stylename="bordered_scrollpanel" height="68dpi_px" width="213dpi_px" left="16dpi_px">
          <ChildGadgets>
            <Image stylename="image" layout_id="addon_image" layout_guid="51a292c3-1626-406f-8bf8-5db11b2d1480" left="1px" right="1px" top="1px" bottom="1px" image_flags="Stretch, Centre" image="" />
          </ChildGadgets>
        </ScrollPanel>
        <StackPanel stylename="stack_panel" left="261dpi_px" stack_resize="ResizeAll">
          <ChildGadgets>
            <StackPanel stylename="stack_panel" left="0px" stack_order="TopToBottom" stack_resize="ResizeAll" width_min="190dpi_px">
              <ChildGadgets>
                <Label stylename="label_addon_header" layout_id="label_name" height="22px" width="97px" top="4px" margin_top="4dpi_px" margin_bottom="4dpi_px" localise_caption="" />
                <Label stylename="label" layout_id="label_available" layout_guid="29278b34-4c16-4a5e-88cd-83596fd789af" height="16px" width="51px" top="30px" localise_caption="addon_available" />
                <LinkLabel stylename="link_label" layout_id="link_label" height="16px" width="188px" top="46px" localise_caption="" url="" />
              </ChildGadgets>
            </StackPanel>
            <StackPanel stylename="stack_panel" height="41dpi_px" left="220px" margin_left="32dpi_px" margin_top="16dpi_px" stack_order="TopToBottom" stack_resize="ResizeWidth">
              <ChildGadgets>
                <StackPanel stylename="stack_panel" height="26dpi_px" left="845px" top="0px" stack_order="RightToLeft" stack_resize="ResizeAll">
                  <ChildGadgets>
                    <Button stylename="button_up" layout_id="button_update" layout_guid="c9d5cd8e-bf0c-440e-82b2-d32976903f93" localise_tooltip="Marketplace_MyLibrary_UpdateTooltip" width="24dpi_px" right="0px" margin_left="10dpi_px" icon_flags="Stretch, Centre, KeepAspectRatio" icon="Runtime\icon_IDE_refresh.png" />
                    <Button stylename="button_up" layout_id="button_trashbin" layout_guid="2723e0b6-98d6-4bb6-9eca-e62a91dfd5fd" localise_tooltip="MarketplaceAsset_RemoveTooltip" width="24dpi_px" right="34px" margin_left="10dpi_px" icon_flags="Stretch, Centre, KeepAspectRatio" icon="trashbin.png" />
                    <Button stylename="button_up" layout_id="button_import" layout_guid="e459e098-1cfa-4d13-bd2d-1d32476afa6d" localise_tooltip="Marketplace_MyLibrary_Download" height="24px" width="100dpi_px" right="68px" localise_name="Marketplace_MyLibrary_Download" />
                  </ChildGadgets>
                </StackPanel>
                <ProgressBar stylename="marketplace_progressbar" layout_id="progress_bar" layout_guid="40390ab3-7d18-4797-848c-83e7643a3f97" height="9dpi_px" width="100dpi_px" left="0dpi_px" top="30px" margin_left="" margin_right="" margin_top="6dpi_px" margin_bottom="" colour="#00FFFFFF" bar_style="marketplace_progressbar_bar" frame_style="marketplace_progressbar_frame" />
              </ChildGadgets>
            </StackPanel>
          </ChildGadgets>
        </StackPanel>
      </ChildGadgets>
    <!--</ScrollPanel>-->
  </Layout>
  <Layout layout_name="settings_layout_androidsettingssync" layout_guid="1eaa1650-6fba-4a8e-a55b-5774c23ac2ab">
    <!--<Grid stylename="grid_container" grid_rowlayout="['auto', 'auto']" grid_columnlayout="['300dpi_px', '1*']" grid_resize="ResizeGrid">-->
      <Cell row="0" column="0" flow_index="0">
        <ChildGadgets>
          <Button stylename="button_up" layout_id="syncFromAndroid" layout_guid="34837605-5ab1-4dfa-8f26-66dddbef02db" height="24px" localise_name="preferences_copyfromandroid" />
        </ChildGadgets>
      </Cell>
      <Cell row="0" column="1" flow_index="0">
        <ChildGadgets>
          <Label stylename="label" layout_id="syncFromAndroid_Label" layout_guid="91c69808-cab0-4681-a731-3d4a8e26a480" height="16px" width="296px" localise_caption="preferences_copyfromandroid_label" word_wrap="True" />
        </ChildGadgets>
      </Cell>
      <Cell row="1" column="0" flow_index="0">
        <ChildGadgets>
          <Button stylename="button_up" layout_id="syncFromAmazon" layout_guid="3471ed3a-53c4-447e-8779-2fb3c11ae70a" height="24px" localise_name="preferences_copyfromamazon" />
        </ChildGadgets>
      </Cell>
      <Cell row="1" column="1" flow_index="0">
        <ChildGadgets>
          <Label stylename="label" layout_id="syncFromAmazon_Label" layout_guid="bdb31820-e164-44e6-9539-aa7611ef1cf5" height="16px" width="298px" localise_caption="preferences_copyfromamazon_label" word_wrap="True" />
        </ChildGadgets>
      </Cell>
    <!--</Grid>-->
  </Layout>
  <Layout layout_name="settings_layout_androidtoolsversion" layout_guid="1eaa1650-6fba-4a8e-a55b-5774c23ac2ac">
    <!--<Grid stylename="grid_container" grid_rowlayout="['auto']" grid_columnlayout="['300dpi_px', '300dpi_px']" column_spacing="6dpi_px" grid_resize="ResizeGrid">-->
    <Cell row="0" column="0" flow_index="0">
      <ChildGadgets>
        <ComboBox stylename="combobox_panel" layout_id="versionToUse" layout_guid="24e5b1dc-076c-40c6-8663-884126721c4a" width="">
          <ListBoxItems />
        </ComboBox>
      </ChildGadgets>
    </Cell>
    <Cell row="0" column="1" flow_index="0">
      <ChildGadgets>
        <Label stylename="label" left="0px" height="16dpi_px" width="148px" localise_caption="preferences_updateandroidtoolsversion" />
      </ChildGadgets>
    </Cell>
    <!--</Grid>-->
  </Layout>
	<Layout layout_name="settings_layout_multilayer_icon_generator_android" layout_guid="93d5c0f1-b6ca-40ac-9b73-6d71be9e6758">
		<!--<Grid stylename="grid_container" height="300dpi_px" width="600dpi_px" grid_rowlayout="['112dpi_px', '48dpi_px']">-->
			<Cell row="0" column="0" flow_index="0">
				<ChildGadgets>
					<Grid stylename="grid_container" height="112dpi_px" width="600dpi_px" left="0px" top="0px" grid_rowlayout="['16dpi_px', '32dpi_px', '48dpi_px']" grid_columnlayout="['1*', '1*']" row_spacing="6dpi_px" column_spacing="12dpi_px">
						<Cell row="0" column="0" flow_index="0">
							<ChildGadgets>
								<Label stylename="label" height="16px" width="142px" left="0px" bottom="0dpi_px" localise_caption="preferences_android_genadaptive_icon" />
							</ChildGadgets>
						</Cell>
						<Cell row="0" column="1" flow_index="0">
							<ChildGadgets>
								<Label stylename="label" height="16px" width="186px" left="0px" bottom="0dpi_px" localise_caption="preferences_android_genadaptive_bg" />
							</ChildGadgets>
						</Cell>
						<Cell row="1" column="0" flow_index="0">
							<ChildGadgets>
								<FileInputGadget stylename="file_input" layout_id="icon_file" layout_guid="d7eba41f-ba0c-44d4-b417-7d9f50f6251b" />
							</ChildGadgets>
						</Cell>
						<Cell row="1" column="1" flow_index="0">
							<ChildGadgets>
								<FileInputGadget stylename="file_input" layout_id="bg_file" layout_guid="9715f6ba-941e-4ccb-b2ea-2eb02e48f4bd" />
							</ChildGadgets>
						</Cell>
						<Cell row="2" column="0" flow_index="0">
							<ChildGadgets>
								<StackPanel stylename="stack_panel" layout_id="preview_toggle" layout_guid="ad21fb86-2829-4046-b451-a8cf09613a7b" height="20dpi_px" width="100%" left="0dpi_px" top="0dpi_px">
									<ChildGadgets>
										<Label stylename="label" layout_id="preview_toggle_label" width="128px" left="14px" top="0px" margin_left="0dpi_px" localise_caption="preferences_android_genadaptive_preview" auto_size="False" />
									</ChildGadgets>
								</StackPanel>
								<ComboBox stylename="combobox_panel" layout_id="mask_list" layout_guid="335eef06-1016-4c23-a891-372a9a90975b" width="75%" left="0dpi_px" bottom="0dpi_px">
									<ListBoxItems />
								</ComboBox>
							</ChildGadgets>
						</Cell>
						<Cell row="2" column="1" flow_index="0">
							<ChildGadgets>
								<Button stylename="button_up" layout_id="gen_btn" layout_guid="1c90b1a5-5193-47df-b762-9e61496cc547" width="50%" right="0dpi_px" top="0dpi_px" localise_name="preferences_android_genadaptive_btn" />
							</ChildGadgets>
						</Cell>
					</Grid>
				</ChildGadgets>
			</Cell>
			<Cell row="1" column="0" flow_index="0">
				<ChildGadgets>
					<Grid stylename="grid_container" layout_id="preview_grid" layout_guid="8ea8aa01-5b52-4ace-b240-3c93011586df" height="175dpi_px" width="600dpi_px" top="8dpi_px" margin_top="0dpi_px" grid_columnlayout="['1*', '1*', '1*']" row_spacing="6dpi_px" column_spacing="6dpi_px"></Grid>
				</ChildGadgets>
			</Cell>
		<!--</Grid>-->
	</Layout>
  <Layout layout_name="settings_layout_windowsuapcertificate" layout_guid="558b3a3e-8cd4-42db-be2d-c2fdc4e83b74">
    <ChildGadgets>
      <StackPanel stylename="settings_gadget_stack_panel">
        <Gadgets>
          <TextBox stylename="text_box" layout_id="setting_value" layout_guid="555075f0-6741-40cd-a17c-a7f4e7dea993" width="300dpi_px" left="5dpi_px" margin_left="5dpi_px" margin_right="5dpi_px" />
          <Button stylename="button_up" layout_id="browse_button" layout_guid="f97d41d4-964d-4d5b-98c8-b5ca67d4eda7" height="24dpi_px" width="50dpi_px" left="315dpi_px" margin_left="5dpi_px" margin_right="5dpi_px" name="..." />
          <Label stylename="label" layout_id="setting_label" layout_guid="314bb3e9-9f3f-40ff-ac36-d389b9d0cdd1" height="16dpi_px" width="0dpi_px" left="375dpi_px" margin_left="5dpi_px" margin_right="5dpi_px" />
        </Gadgets>
      </StackPanel>
      <Button stylename="button_up" layout_id="install_button" layout_guid="be277756-8f76-417d-b6a2-6d472ce64d1e" height="24dpi_px" width="100dpi_px" left="385dpi_px" margin_left="5dpi_px" margin_right="5dpi_px" localise_name="ggs_certificate_install" />
    </ChildGadgets>
  </Layout>
  <Layout layout_name="settings_layout_text_string" layout_guid="4b09adf5-fb13-4e34-8515-34f6bd927eab">
    <StackPanel stylename="settings_gadget_stack_panel">
      <Gadgets>
        <TextBox stylename="text_box" layout_id="setting_value" layout_guid="10774180-3be4-4125-bd36-6b99a29769e3" width="200dpi_px" left="0dpi_px" margin_right="10dpi_px" />
        <Label stylename="settings_gadget_label" layout_id="setting_label" layout_guid="1b755df1-29f7-4068-b06d-14355f5646e1" height="16dpi_px" width="0dpi_px" left="215dpi_px" margin_left="5dpi_px" />
      </Gadgets>
    </StackPanel>
  </Layout>
  <Layout layout_name="settings_group_layout" layout_guid="2e337b26-7f9d-4720-b97f-69c9aa9aeaa1">
    <Gadgets>
      <Group>
        <ChildGadgets>
          <StackPanel stylename="resizing_stack_panel" stack_order="TopToBottom" layout_id="settings_group_panel" margin="10dpi_px" />
        </ChildGadgets>
      </Group>
    </Gadgets>
  </Layout>
  <Layout layout_name="prefs_tree_layout" layout_guid="87231a9d-44dc-4214-8847-edb1380e0308">
    <Window stylename="prefs_window" height="600dpi_px" width="820dpi_px" localise_title="PrefsTree_Title" window_flags="CloseButton, ResizeButton, ScrollBars, DockingDisabled">
      <Client>
        <ChildGadgets>
          <Grid stylename="grid_container" layout_id="settings_content_grid" layout_guid="ace0c155-7af0-43ff-ae55-2b73fd480214" grid_rowlayout="['50dpi_px', 'auto', '40dpi_px']" grid_columnlayout="['140dpi_px', '1*']" splitter_thickness="14dpi_px">
            <ColumnDockSplitter stylename="dock_splitter" height="514px" width="5dpi_px" left="140px" top="0px" splitter_anchor="First" row="0" column="1" rowspan="2" columnspan="1" />
            <Cell row="0" column="1" flow_index="0">
              <Gadgets>
                <ScrollPanel stylename="bordered_scrollpanel" bottom="16dpi_px">
                  <ChildGadgets>
                    <Grid stylename="grid_container" grid_columnlayout="['1.4*', '1*']" grid_resize="ResizeGrid">
                      <Cell row="0" column="0" flow_index="0">
                        <ChildGadgets>
                          <Label stylename="basic_label" layout_id="content_label" layout_guid="21059ee5-dfda-4235-a259-c6cc95ad80fe" height="16px" width="0px" left="10dpi_px" />
                        </ChildGadgets>
                      </Cell>
                      <Cell row="0" column="1" flow_index="0">
                        <ChildGadgets>
                          <Button stylename="button_up" layout_id="restore_defaults" layout_guid="25f4b540-cc96-4e91-9149-1cd4bcde6fc0" height="24px" width="100%" left="0dpi_px" right="20dpi_px" localise_name="restoredefaults" />
                        </ChildGadgets>
                      </Cell>
                    </Grid>
                  </ChildGadgets>
                </ScrollPanel>
              </Gadgets>
            </Cell>
            <Cell row="1" column="1" flow_index="0">
              <Gadgets>
                <TreeView stylename="gadget_treeview" layout_id="content_tree" layout_guid="c92fd882-e67a-4e66-826f-7aeeb9dbf10c" />
              </Gadgets>
            </Cell>
            <Cell row="2" column="1" flow_index="0">
              <Gadgets>
                <Button stylename="" layout_id="pref_apply_button" layout_guid="2fca907c-fcc9-4421-a132-bf344d733ceb" height="24px" width="100dpi_px" left="20dpi_px" localise_name="Button_Apply" />
                <Button stylename="button_up" layout_id="pref_cancel_button" layout_guid="2686ca2b-d55a-439c-98ed-c6b24261fec4" height="24px" width="100dpi_px" right="20dpi_px" localise_name="Button_Cancel" />
                <Button stylename="button_up" layout_id="pref_ok_button" layout_guid="d0ad1185-2123-41ba-8b5c-38169af63f0b" height="24px" width="100dpi_px" right="140dpi_px" localise_name="Button_OK" />
              </Gadgets>
            </Cell>
            <Cell row="0" column="0" rowspan="2" columnspan="1" flow_index="0">
              <Gadgets>
                <TreeView stylename="gadget_treeview" layout_id="settings_tree" layout_guid="7245976d-4625-45c8-9e09-9f95cf049fcb" />
              </Gadgets>
            </Cell>
          </Grid>
        </ChildGadgets>
      </Client>
      <Layout layout_name="BasicWindowFrame" layout_guid="f0695f87-de65-4a48-a3a8-9bd5cb5a8d8c" />
    </Window>
  </Layout>
  <Layout layout_name="settings_layout_text_path" layout_guid="00adc2b1-8ea1-4991-bfe6-2da0cc4642ec">
    <Grid stylename="grid_container" height="20dpi_px" width="100%" grid_rowlayout="['auto']" grid_columnlayout="['auto', 'auto', 'auto']" column_spacing="10dpi_px" grid_resize="ResizeGrid">
      <Cell row="0" column="0" flow_index="0">
        <ChildGadgets>
          <TextBox stylename="basic_text_box" layout_id="setting_value" layout_guid="1eefef00-1371-4d39-aedc-65e95457503d" width="350dpi_px" left="0dpi_px" />
        </ChildGadgets>
      </Cell>
      <Cell row="0" column="1" flow_index="0">
        <Gadgets>
          <Button stylename="settings_browse_button" layout_id="setting_button" layout_guid="f07a3e3e-9a05-4d67-a3b8-6bbd1d6478c4" height="24px" left="0dpi_px" />
        </Gadgets>
      </Cell>
      <Cell row="0" column="2" flow_index="0">
        <Gadgets>
          <Label stylename="settings_gadget_label" layout_id="setting_label" layout_guid="3147f025-7b11-4479-9b54-1066b84a6871" height="16px" width="27px" margin_left="5dpi_px" />
        </Gadgets>
      </Cell>
    </Grid>
  </Layout>
  <Layout layout_name="gameoptions_tree_layout" layout_guid="5f071a9d-44dc-4214-8847-edb1380e0308">
    <Window stylename="prefs_window" height="600dpi_px" width="800dpi_px" localise_title="PrefsTree_Title" window_flags="CloseButton, ResizeButton, ScrollBars, DockingDisabled, Bookmark" accept_button_id="pref_ok_button">
      <Client>
        <ChildGadgets>
          <!--<Grid stylename="grid_container" layout_id="settings_content_grid" layout_guid="6ba105da-d838-4494-970a-ff06852e5f58" grid_rowlayout="['50dpi_px', 'auto', '40dpi_px']" grid_columnlayout="['140dpi_px', 'auto']">-->
          <Grid stylename="grid_container" layout_id="settings_content_grid" grid_rowlayout="['50dpi_px', 'auto', '40dpi_px']" grid_columnlayout="['140dpi_px', 'auto']" splitter_thickness="14dpi_px">
            <ColumnDockSplitter stylename="dock_splitter" height="517dpi_px" width="14dpi_px" left="140dpi_px" top="0dpi_px" row="0" column="1" rowspan="2" columnspan="1" splitter_anchor="First" />
            <Cell row="0" column="1" flow_index="0">
              <Gadgets>
                <Label stylename="basic_label" layout_id="content_label" layout_guid="21059ee5-dfda-4235-a259-c6cc95ad80fe" height="16dpi_px" width="0dpi_px" left="10dpi_px" />
              </Gadgets>
            </Cell>
            <Cell row="1" column="1" flow_index="0">
              <Gadgets>
                <TreeView stylename="gadget_treeview" layout_id="content_tree" layout_guid="c92fd882-e67a-4e66-826f-7aeeb9dbf10c" />
              </Gadgets>
            </Cell>
            <Cell row="2" column="1" flow_index="0">
              <Gadgets>
                <Button stylename="" layout_id="pref_apply_button" layout_guid="030a6f80-ce71-4458-bb63-e2d534ea79f1" height="24px" width="100dpi_px" left="20dpi_px" localise_name="Button_Apply" />
                <Button stylename="button_up" layout_id="pref_cancel_button" layout_guid="e0f6c7e0-315d-4444-b093-785b9a4134b8" height="24px" width="100dpi_px" right="20dpi_px" localise_name="Button_Cancel" />
                <Button stylename="button_up" layout_id="pref_ok_button" layout_guid="d05be168-9c05-4a59-a33e-5d2f7bd62353" height="24px" width="100dpi_px" right="140dpi_px" localise_name="Button_OK" />
              </Gadgets>
            </Cell>
            <Cell row="0" column="0" rowspan="2" columnspan="1">
              <Gadgets>
                <TreeView stylename="gadget_treeview" layout_id="settings_tree" layout_guid="7245976d-4625-45c8-9e09-9f95cf049fcb" />
              </Gadgets>
            </Cell>
          </Grid>
        </ChildGadgets>
      </Client>
      <Layout layout_name="BasicWindowFrame" layout_guid="f0695f87-de65-4a48-a3a8-9bd5cb5a8d8c" />
    </Window>
  </Layout>
  <Layout layout_name="settings_layout_guid_gadget" layout_guid="e36e9384-4242-5454-85f9-590e7f94d2a5">
    <Gadgets>
      <TextBox stylename="settings_textbox_style" layout_id="setting_value" margin_right="10dpi_px" width="255dpi_px" />
      <Button stylename="button_up" layout_id="generate_guid" layout_guid="f97d41d4-2323-4d5b-7777-b5ca67d4eda7" height="24dpi_px" width="130dpi_px" left="315dpi_px" margin_left="5dpi_px" margin_right="5dpi_px" localise_name="ggs_new_guid" />
      <Label stylename="settings_gadget_label" layout_id="setting_label" margin_left="10dpi_px" height="16dpi_px" localise_caption="Option_Project_GUID" />
    </Gadgets>
  </Layout>
  <Layout layout_name="settings_layout_combobox" layout_guid="27c4c174-2608-42ca-8607-91edf0638425">
    <Gadgets>
      <ComboBox stylename="combobox_panel" layout_id="setting_value" layout_guid="bddd96a1-7555-429d-a2c6-b7aebb73f646" width="320dpi_px">
        <ListBoxItems />
      </ComboBox>
      <Label stylename="label" layout_id="setting_name" layout_guid="6c93c7ce-00ea-4962-96ef-11f91eb68f25" height="25px" width="42px" left="501px" margin_left="10dpi_px" />
    </Gadgets>
  </Layout>
  <Layout layout_name="settings_layout_RuntimeFeedManagement" layout_guid="643b99ac-7ed0-48db-861c-dd88c0811f3f">
    <Cell row="0" column="0" flow_index="0">
      <ChildGadgets>
        <Button stylename="button_up" layout_id="add" layout_guid="355ea9a2-8363-471b-991e-e39a88448f3e" height="24px" width="80dpi_px" right="10dpi_px" top="6dpi_px" margin_top="6dpi_px" margin_bottom="6dpi_px" localise_name="Button_Add" />
      </ChildGadgets>
    </Cell>
    <Cell row="1" column="0" flow_index="0">
      <ChildGadgets>
        <StackPanel stylename="stack_panel" layout_id="list" layout_guid="3e4174d8-dcf2-4802-a6b7-966dcc65945f" left="0dpi_px" top="0dpi_px" stack_order="TopToBottom" stack_resize="ResizeHeight" />
      </ChildGadgets>
    </Cell>
  </Layout>
  <Layout layout_name="settings_layout_text_hex" layout_guid="3a13e471-e9e0-4288-8777-6acde5ac15e7">
    <StackPanel stylename="settings_gadget_stack_panel">
      <Gadgets>
        <NumericTextBox layout_id="setting_value" layout_guid="b9bb8227-7b4b-4e8c-a139-eb61341cd5aa" width="100dpi_px" left="0dpi_px" margin_right="10dpi_px" input_type="Hex" />
        <Label stylename="settings_gadget_label" layout_id="setting_label" layout_guid="e1625b74-558d-4136-b7d3-9cb3bb6fb79a" height="16dpi_px" width="0dpi_px" left="115dpi_px" margin_left="5dpi_px" />
      </Gadgets>
    </StackPanel>
  </Layout>
  <Layout layout_name="settings_layout_radiogroup" layout_guid="b81f500f-e105-4a08-bed8-88ee4b0fe24a">
    <ChildGadgets>
      <StackPanel stylename="settings_gadget_stack_panel_vertical" stack_order="TopToBottom">
        <ChildGadgets>
          <Label stylename="settings_gadget_radiogroup_label" layout_id="setting_label" height="16dpi_px" width="61dpi_px" />
          <StackPanel stylename="settings_gadget_stack_panel_vertical" stack_order="TopToBottom" layout_id="stack" />
        </ChildGadgets>
      </StackPanel>
    </ChildGadgets>
  </Layout>
  <Layout layout_name="settings_layout_Enum_listbox" layout_guid="2b40eb01-6cfd-4a88-8463-d3f2f3a49004">
    <StackPanel stylename="settings_gadget_stack_panel_vertical" height="100dpi_px">
      <Gadgets>
        <Label stylename="settings_gadget_label" layout_id="setting_label" />
        <ListBox layout_id="setting_value" width="320dpi_px" height="100%" margin_bottom="4dpi_px" />
      </Gadgets>
    </StackPanel>
  </Layout>
  <Layout layout_name="settings_layout_dpi_override" layout_guid="51f1e083-c37c-4e82-998f-6ddb7b025d9f">
    <ChildGadgets>
      <Grid stylename="grid_container" left="0dpi_px" top="0dpi_px" grid_rowlayout="['auto', 'auto', 'auto']" row_spacing="6dpi_px" grid_resize="ResizeGrid">
        <Cell row="0" column="0" flow_index="0">
          <ChildGadgets>
            <CheckBox stylename="checkbox_stack" layout_id="enable_override" layout_guid="68eb026f-2670-4718-9b0d-4ddf6d5bd29f" left="0px" top="0px" localise_name="dpi_override" />
          </ChildGadgets>
        </Cell>
        <Cell row="1" column="0" flow_index="0">
          <ChildGadgets>
            <StackPanel stylename="stack_panel" left="0dpi_px" stack_resize="ResizeAll">
              <ChildGadgets>
                <Slider stylename="dpioverride_slider" layout_id="override_value" layout_guid="9240b6b6-6418-4a66-9cd0-181146fd6e87" width="160dpi_px" left="0px" min_value="50" max_value="500" value="100" click_increment="10" mindrag_increment="1" slider_float_precision="0"/>
                <Label stylename="label" height="16px" width="85px" left="166px" margin_left="6dpi_px" localise_caption="dpi_percentage" />
              </ChildGadgets>
            </StackPanel>
          </ChildGadgets>
        </Cell>
        <Cell row="2" column="0" flow_index="0">
          <ChildGadgets>
            <StackPanel stylename="stack_panel" left="0dpi_px" stack_resize="ResizeAll">
              <ChildGadgets>
                <NumericTextBox stylename="numeric_text_box" layout_id="raw_dpi" layout_guid="d4b6e2b6-3755-4cf2-80f3-9cf73dd1b655" left="0px" has_buttons="True" step_increment="24" text="96" default_value="96" min="48" max="480" />
                <Label stylename="label" height="16px" width="78px" left="71px" margin_left="6dpi_px" localise_caption="dpi_raw" />
              </ChildGadgets>
            </StackPanel>
          </ChildGadgets>
        </Cell>
      </Grid>
    </ChildGadgets>
  </Layout>
  <Layout layout_name="settings_layout_Enum_dropdown" layout_guid="67f7ba8a-738f-4971-941c-ce815fbf68ee">
    <StackPanel stylename="settings_gadget_stack_panel">
      <Gadgets>
        <ComboBox stylename="combobox_panel" layout_id="setting_value" layout_guid="53daef91-ce65-4d7d-bf44-b2717621861f" width="200dpi_px" left="0dpi_px">
          <ListBoxItems />
        </ComboBox>
        <Label stylename="settings_gadget_label" layout_id="setting_label" layout_guid="7da59951-c9c9-4a85-af42-7db2d3b22592" width="400dpi_px" height="16dpi_px" margin_left="15dpi_px" word_wrap="True" />
      </Gadgets>
    </StackPanel>
  </Layout>
  <Layout layout_name="settings_layout_textstyle" layout_guid="3ba62d39-c7bb-49d5-ba12-7e204f6ead32">
    <ChildGadgets>
      <StackPanel stylename="settings_gadget_stack_panel_vertical">
        <Gadgets>
          <StackPanel stylename="settings_gadget_stack_panel" top="10dpi_px" margin_left="10dpi_px" margin_right="10dpi_px" margin_top="10dpi_px" margin_bottom="10dpi_px">
            <Gadgets>
              <Label stylename="settings_gadget_label" height="16dpi_px" width="35dpi_px" localise_caption="FontStyle_Colour" />
              <ColourSelectButton stylename="colour_select_button_up" layout_id="colour_setting" layout_guid="c7dd3e1c-3bbc-44fe-8ea7-d5d97158f027" left="120dpi_px" />
            </Gadgets>
          </StackPanel>
          <StackPanel stylename="settings_gadget_stack_panel" height="30dpi_px" top="42dpi_px" margin_left="10dpi_px" margin_right="10dpi_px" margin_top="0dpi_px" margin_bottom="10dpi_px" stack_resize="ResizeWidth">
            <Gadgets>
              <Label stylename="settings_gadget_label" height="16dpi_px" width="59dpi_px" localise_caption="FontStyle_Name" />
              <ComboBox stylename="combobox_panel" layout_id="font_name_setting" layout_guid="04297144-d0a4-498d-8b14-bf2fc2269e31" width="320dpi_px" left="120dpi_px" top="0dpi_px">
                <ListBoxItems />
              </ComboBox>
            </Gadgets>
          </StackPanel>
          <StackPanel stylename="settings_gadget_stack_panel" height="30dpi_px" top="86dpi_px" margin_left="10dpi_px" margin_right="10dpi_px" margin_top="0dpi_px" margin_bottom="10dpi_px">
            <Gadgets>
              <Label stylename="settings_gadget_label" height="16dpi_px" width="26dpi_px" localise_caption="fonteditor_stylename" />
              <ComboBox stylename="combobox_panel" layout_id="font_style_setting" layout_guid="7a21aae0-e93d-48af-ac2b-f930dc886859" left="120dpi_px" top="0dpi_px">
                <ListBoxItems />
              </ComboBox>
            </Gadgets>
          </StackPanel>
          <StackPanel stylename="settings_gadget_stack_panel" height="30dpi_px" top="128dpi_px" margin_left="10dpi_px" margin_right="10dpi_px" margin_top="0dpi_px" margin_bottom="10dpi_px">
            <Gadgets>
              <Label stylename="settings_gadget_label" height="16dpi_px" width="22dpi_px" localise_caption="fonteditor_size" />
              <ComboBox stylename="combobox_panel" layout_id="font_size_setting" layout_guid="2509c808-58e8-4ed2-980e-c04fb73ba89c" left="120dpi_px" min="1" max="200">
                <ListBoxItems />
              </ComboBox>
            </Gadgets>
          </StackPanel>
          <StackPanel stylename="settings_gadget_stack_panel" height="30dpi_px" left="82dpi_px" top="162dpi_px" margin_left="10dpi_px" margin_right="10dpi_px" margin_top="0dpi_px" margin_bottom="10dpi_px">
            <Gadgets>
              <Label stylename="settings_gadget_label" height="16dpi_px" width="103dpi_px" localise_caption="fonteditor_render_mode" />
              <RadioGroup stylename="group_box" layout_id="font_aa_setting" layout_guid="8ce22593-a2a4-455d-8f06-0d419880ed35" height="31dpi_px" width="332dpi_px" left="120dpi_px" top="0dpi_px">
                <ChildGadgets>
                  <StackPanel stylename="resizing_stack_panel" height="30dpi_px" left="0dpi_px" right="0dpi_px" top="0dpi_px" bottom="0dpi_px">
                    <ChildGadgets>
                      <RadioButton stylename="radiobutton_stack" layout_id="radio_aa_default" layout_guid="e9346986-6180-4161-8428-91b5b21c65d3" margin_top="5dpi_px" margin_bottom="5dpi_px" localise_name="fonteditor_aa_default" />
                      <RadioButton stylename="radiobutton_stack" layout_id="radio_aa_on" layout_guid="c561fff2-6b22-42e9-bd75-911de9e4bcfe" left="237dpi_px" margin_top="5dpi_px" margin_bottom="5dpi_px" localise_name="fonteditor_aa_on" />
                      <RadioButton stylename="radiobutton_stack" layout_id="radio_aa_off" layout_guid="9c24ab14-1ab1-4fe8-9bec-d31f1ce19d3e" left="284dpi_px" margin_top="5dpi_px" margin_bottom="5dpi_px" localise_name="fonteditor_aa_off" />
                    </ChildGadgets>
                  </StackPanel>
                </ChildGadgets>
              </RadioGroup>
            </Gadgets>
          </StackPanel>
        </Gadgets>
      </StackPanel>
    </ChildGadgets>
  </Layout>
  <Layout layout_name="settings_layout_weblink" layout_guid="4b09adf5-fb13-4e34-8515-34f6bd927fab">
    <LinkLabel layout_id="setting_value" layout_guid="4b09adf5-fb13-4e34-8515-34f6bd927fad" />
  </Layout>
  <Layout layout_name="settings_layout_text_int" layout_guid="c03017a7-b908-4302-882a-1c6f4bd4c587">
    <StackPanel stylename="settings_gadget_stack_panel">
      <Gadgets>
        <NumericTextBox layout_id="setting_value" layout_guid="75559e22-9bbe-45e8-bab5-7d798a64fe92" width="100dpi_px" left="0dpi_px" top="0dpi_px" margin_right="10dpi_px" />
        <Label stylename="settings_gadget_label" layout_id="setting_label" layout_guid="40eb21a4-3d64-46c5-807b-a3a10dcdc921" height="16dpi_px" width="0dpi_px" left="115dpi_px" margin_left="5dpi_px" />
      </Gadgets>
    </StackPanel>
  </Layout>
  <Layout layout_name="settings_layout_label" layout_guid="1351dcef-a5c9-4e7b-bae2-dff11fcb7671">
    <Label stylename="settings_gadget_label" layout_id="setting_value" layout_guid="3147f025-7b11-4479-9b54-1066b84a6872" height="16px" width="27px" margin_left="5dpi_px" />
  </Layout>
  <Layout layout_name="settings_layout_steam_id" layout_guid="4b09adf5-fb13-4e34-8515-34f6bd927bab">
    <Gadgets>
      <TextBox stylename="text_box" layout_id="setting_value" layout_guid="10774180-3be4-4125-bd36-6b99a29769e2" width="400dpi_px" left="0dpi_px" margin_right="10dpi_px" />
      <Label stylename="settings_gadget_label" layout_id="setting_label" layout_guid="1b755df1-29f7-4068-b06d-14355f5646e3" height="16dpi_px" width="0dpi_px" left="415dpi_px" margin_left="5dpi_px" />
    </Gadgets>
  </Layout>
  <Layout layout_name="settings_layout_mac_provisioning" layout_guid="9f4fbbe2-4f3f-4b79-8473-8a4cf804212f">
    <ChildGadgets>
      <StackPanel stylename="settings_gadget_stack_panel">
        <Gadgets>
          <ComboBox stylename="combobox_panel" layout_id="setting_value" layout_guid="d98841e2-a057-48ea-877d-0226533ebabd" width="500dpi_px" left="5dpi_px" margin_left="5dpi_px" margin_right="5dpi_px">
            <ListBoxItems />
          </ComboBox>
          <Label stylename="label" layout_id="setting_label" layout_guid="2e482ff9-9a9c-4bfb-8dac-25d9e443092e" height="16dpi_px" width="0dpi_px" left="0dpi_px" margin_left="5dpi_px" margin_right="5dpi_px" />
          <Button stylename="button_up" layout_id="refresh" layout_guid="1fefba9b-46ef-4a6d-8a59-ade72a6db766" height="24dpi_px" width="100dpi_px" left="15dpi_px" margin_left="5dpi_px" margin_right="5dpi_px" localise_name="ggs_mac_provision_refresh" />
        </Gadgets>
      </StackPanel>
    </ChildGadgets>
  </Layout>
  <Layout layout_name="settings_layout_image_path" layout_guid="724a2fd9-756e-463c-9912-54fa84fffad6">
    <Group stylename="group_box" height="168dpi_px" width="228dpi_px" default_label_style ="group_label_wrapped">
      <ChildGadgets>
        <Label stylename="settings_gadget_label" layout_id="info" layout_guid="19ce864a-483c-4be3-b3b9-4beed47e48f5" height="16dpi_px" width="0dpi_px" left="10dpi_px" top="10dpi_px" />
        <Button stylename="settings_browse_button" layout_id="setting_button" layout_guid="0a8f1f3c-fb6e-4cc2-ad69-5b99a523729a" left="10dpi_px" top="40dpi_px" />
        <Label stylename="settings_gadget_label" layout_id="dimensions" layout_guid="19ce864a-483c-4be3-b3b9-4beed47e48f5" height="16dpi_px" width="0dpi_px" left="10dpi_px" top="80dpi_px" />
        <Image stylename="image" layout_id="setting_value" layout_guid="723c8e24-66d5-4c08-9212-35b35d80decf" height="128dpi_px" width="128dpi_px" left="80dpi_px" top="40dpi_px" margin_left="20dpi_px" margin_right="20dpi_px" margin_top="20dpi_px" margin_bottom="20dpi_px" image="IDE_Toolbar\icon_IDE_save.png" image_flags="Stretch, KeepAspectRatio" />
      </ChildGadgets>
    </Group>
  </Layout>
  <Layout layout_name="settings_layout_text_multiline" layout_guid="55696d42-1af9-475b-aed9-9c9c4921c843">
    <StackPanel stylename="settings_gadget_stack_panel">
      <Gadgets>
        <MultiLineTextBox stylename="multiline_text_box" layout_id="setting_value" width="200dpi_px" left="0dpi_px" top="0dpi_px" margin_right="10dpi_px" />
        <Label stylename="label" layout_id="setting_label" height="16dpi_px" width="0dpi_px" left="215dpi_px" margin_left="5dpi_px" />
      </Gadgets>
    </StackPanel>
  </Layout>
  <Layout layout_name="settings_layout_audio_device_selection" layout_guid="86b7006e-947b-45cf-9903-a6ee4d63c869">
    <ChildGadgets>
      <ComboBox stylename="combobox_panel" layout_id="setting_value" left="0px" width="400dpi_px">
        <ListBoxItems />
      </ComboBox>
      <Button stylename="button_up" layout_id="refresh_button" width="24dpi_px" left="126px" margin_left="6dpi_px" icon_flags="Stretch, Centre, KeepAspectRatio" icon="Runtime\icon_IDE_refresh.png" />
      <Label stylename="label" layout_id="setting_label" height="16px" width="213px" left="156px" margin_left="6dpi_px" localise_caption="default_audio_setting" />
    </ChildGadgets>
  </Layout>
  <Layout layout_name="settings_layout_nsisinstallergadget" layout_guid="91968235-aac5-47c3-9fa8-4d14ebf61b70">
    <!--<Grid stylename="nsisinstallergadget_style">-->
    <Cell row="0" column="0" flow_index="0">
      <ChildGadgets>
        <Grid stylename="grid_container" top="6dpi_px" grid_rowlayout="['auto', 'auto', 'auto', '1*']" grid_columnlayout="['auto']" row_spacing="6dpi_px">
          <Cell row="0" column="0" flow_index="0">
            <ChildGadgets>
              <Image stylename="image" layout_id="installer_finished" layout_guid="88b80a78-b0f7-4f88-a5ee-fc4ddb3f2545" height="314dpi_px" width="164dpi_px" image_flags="Stretch, Resize" />
            </ChildGadgets>
          </Cell>
          <Cell row="1" column="0" flow_index="0">
            <ChildGadgets>
              <Label stylename="label" height="16px" width="54px" caption="164 x 314" />
            </ChildGadgets>
          </Cell>
          <Cell row="2" column="0" flow_index="0">
            <ChildGadgets>
              <Button stylename="button_up" layout_id="installer_finished_browse" layout_guid="89f5ee47-2610-452c-801b-a5453bd986ee" height="24px" width="48dpi_px" name="..." />
            </ChildGadgets>
          </Cell>
        </Grid>
      </ChildGadgets>
    </Cell>
    <Cell row="0" column="1" flow_index="0">
      <ChildGadgets>
        <Grid stylename="grid_container" grid_rowlayout="['auto', 'auto', 'auto', '1*']" row_spacing="6dpi_px" grid_resize="ResizeGrid">
          <Cell row="0" column="0" flow_index="0">
            <ChildGadgets>
              <Grid stylename="grid_container" bottom="0dpi_px" grid_rowlayout="['auto', 'auto', 'auto']" grid_columnlayout="['auto']" row_spacing="6dpi_px" grid_resize="ResizeGrid">
                <Cell row="1" column="0" flow_index="0">
                  <ChildGadgets>
                    <Image stylename="image" layout_id="header_image" layout_guid="fe657858-c6eb-4a8d-863e-a69e9cc5ac74" height="57dpi_px" width="150dpi_px" image_flags="Stretch" />
                  </ChildGadgets>
                </Cell>
                <Cell row="2" column="0" flow_index="0">
                  <ChildGadgets>
                    <Grid stylename="grid_container" top="0dpi_px" grid_rowlayout="['auto', 'auto']" grid_resize="ResizeGrid">
                      <Cell row="0" column="0" flow_index="0">
                        <ChildGadgets>
                          <Label stylename="label" height="16px" width="47px" caption="150 x 57" />
                        </ChildGadgets>
                      </Cell>
                      <Cell row="1" column="0" flow_index="0">
                        <ChildGadgets>
                          <Button stylename="button_up" layout_id="header_image_browse" layout_guid="39732aaf-f45c-48ac-ab8a-651b4d126c5a" height="24px" width="48dpi_px" name="..." />
                        </ChildGadgets>
                      </Cell>
                    </Grid>
                  </ChildGadgets>
                </Cell>
              </Grid>
            </ChildGadgets>
          </Cell>
          <Cell row="1" column="0" flow_index="0">
            <ChildGadgets>
              <StackPanel stylename="stack_panel" stack_order="TopToBottom" stack_resize="ResizeHeight">
                <ChildGadgets>
                  <Grid stylename="grid_container" left="0px" top="0px" grid_rowlayout="['auto']" grid_columnlayout="['auto', '1*', 'auto']" row_spacing="16dpi_px" column_spacing="6dpi_px" grid_resize="ResizeGrid">
                    <Cell row="0" column="0" flow_index="0">
                      <ChildGadgets>
                        <Label stylename="label" height="16px" width="108px" margin_right="10dpi_px" localise_caption="Option_License_Agreement" />
                      </ChildGadgets>
                    </Cell>
                    <Cell row="0" column="1" flow_index="0">
                      <ChildGadgets>
                        <FileInputGadget stylename="file_input" layout_id="license_path" layout_guid="0e253904-e698-4f31-9d2f-1c4e15e329fe" />
                      </ChildGadgets>
                    </Cell>
                    <Cell row="0" column="2" flow_index="0">
                      <ChildGadgets>
                        <Button stylename="button_up" auto_width="true" layout_id="edit_license" layout_guid="7f14c300-c2de-41ef-a70d-c8f8107dbe8a" height="24px" width_min="40dpi_px" margin_right="12dpi_px" localise_name="Edit" />
                      </ChildGadgets>
                    </Cell>
                  </Grid>
                  <Button stylename="button_up" auto_width="true" layout_id="ResetLicense" layout_guid="a2a8b227-5142-45aa-81ea-f3b01c4177a4" height="24px" width_min="200dpi_px" left="4dpi_px" top="34px" margin_top="10dpi_px" localise_name="UseDefaultLicenseAgreement" />
                </ChildGadgets>
              </StackPanel>
            </ChildGadgets>
          </Cell>
          <Cell row="2" column="0" flow_index="0">
            <ChildGadgets>
              <StackPanel stylename="stack_panel" margin_top="30dpi_px" margin_bottom="30dpi_px" stack_order="TopToBottom" stack_resize="ResizeHeight">
                <ChildGadgets>
                  <Grid stylename="grid_container" left="0px" top="0px" grid_rowlayout="['auto']" grid_columnlayout="['auto', '1*', 'auto']" column_spacing="6dpi_px" grid_resize="ResizeGrid">
                    <Cell row="0" column="0" flow_index="0">
                      <ChildGadgets>
                        <Label stylename="label" height="16px" width="61px" margin_right="10dpi_px" localise_caption="Option_NSIS_Script" />
                      </ChildGadgets>
                    </Cell>
                    <Cell row="0" column="1" flow_index="0">
                      <ChildGadgets>
                        <FileInputGadget stylename="file_input" layout_id="install_script_path" layout_guid="1b628f98-5f27-4428-96ad-6254e543a45c" />
                      </ChildGadgets>
                    </Cell>
                    <Cell row="0" column="2" flow_index="0">
                      <ChildGadgets>
                        <Button stylename="button_up" auto_width="true" layout_id="edit_scripts" layout_guid="b7ad3f16-ccfc-4d30-a0ab-430b97ab5b30" height="24px" width_min="40dpi_px" margin_right="12dpi_px" localise_name="Edit" />
                      </ChildGadgets>
                    </Cell>
                  </Grid>
                  <Button stylename="button_up" auto_width="true" layout_id="ResetScript" layout_guid="24137de3-b187-41e3-9e1c-3633e8d468a5" height="24px" width_min="200dpi_px" left="4dpi_px" top="34px" margin_top="10dpi_px" localise_name="UseDefaultNSISScript" />
                </ChildGadgets>
              </StackPanel>
            </ChildGadgets>
          </Cell>
        </Grid>
      </ChildGadgets>
    </Cell>
    <!--</Grid>-->
  </Layout>
  <Layout layout_name="settings_layout_betachannelgadget" layout_guid="91968235-aac5-47c3-9fa8-4d14ebf61b71">
    <!--<Grid stylename="betachannelgadget_style" grid_rowlayout="['auto', 'auto', 'auto', 'auto', 'auto', 'auto', 'auto', '42dpi_px', 'auto', 'auto']">-->
      <Cell row="0" column="0" flow_index="0">
        <ChildGadgets>
          <Image stylename="image" height="134px" width="652px" image="betachannelheader.png" />
        </ChildGadgets>
      </Cell>
      <Cell row="1" column="0" flow_index="0">
        <ChildGadgets>
          <Label stylename="label" height="16px" width="" left="6dpi_px" localise_caption="beta_1" word_wrap="True" />
        </ChildGadgets>
      </Cell>
      <Cell row="2" column="0" flow_index="0">
        <ChildGadgets>
          <Label stylename="label" height="16px" width="" left="6dpi_px" localise_caption="beta_2" word_wrap="True" />
        </ChildGadgets>
      </Cell>
      <Cell row="3" column="0" flow_index="0">
        <ChildGadgets>
          <StackPanel stylename="stack_panel" left="6dpi_px" stack_resize="ResizeAll">
            <ChildGadgets>
              <Label stylename="label" height="16px" width="" left="0px" localise_caption="beta_3" word_wrap="True" />
              <LinkLabel stylename="link_label" height="16px" width="219dpi_px" left="409px" margin_left="6dpi_px" localise_caption="beta_7" word_wrap="True" url="https://www.yoyogames.com/legal/eula" open_in_external_browser="True" />
            </ChildGadgets>
          </StackPanel>
        </ChildGadgets>
      </Cell>
      <Cell row="4" column="0" flow_index="0">
        <ChildGadgets>
          <Label stylename="label" height="16px" width="" left="6dpi_px" localise_caption="beta_4" word_wrap="True" />
        </ChildGadgets>
      </Cell>
      <Cell row="5" column="0" flow_index="0">
        <ChildGadgets>
          <Label stylename="label" layout_id="boldlabel" layout_guid="2e4d3799-75dd-4d60-b9e6-942db7a4b49d" height="16px" width="" left="6dpi_px" localise_caption="beta_5" word_wrap="True" />
        </ChildGadgets>
      </Cell>
      <Cell row="6" column="0" flow_index="0">
        <ChildGadgets>
          <Label stylename="label" height="16px" width="" left="6dpi_px" localise_caption="beta_6" word_wrap="True" />
        </ChildGadgets>
      </Cell>
      <Cell row="7" column="0" flow_index="0">
        <ChildGadgets>
          <CheckBox stylename="checkbox_stack" layout_id="corrupt" layout_guid="8d0514e5-0a95-4bda-aa77-967869ba41ce" left="42dpi_px" bottom="0dpi_px" localise_name="beta_check_1" />
        </ChildGadgets>
      </Cell>
      <Cell row="8" column="0" flow_index="0">
        <ChildGadgets>
          <CheckBox stylename="checkbox_stack" layout_id="backup" layout_guid="ec3f148c-605a-4161-ad3e-87869c56b398" left="42dpi_px" localise_name="beta_check_2" />
        </ChildGadgets>
      </Cell>
      <Cell row="9" column="0" flow_index="0">
        <ChildGadgets>
          <ToggleButton stylename="button_up" layout_id="agreement" layout_guid="d625ac2c-a94a-4565-b63a-397e172742f2" width="50%" left="42dpi_px" localise_name="beta_check_opt-in" />
        </ChildGadgets>
      </Cell>
    <!--</Grid>-->
  </Layout>
  <Layout layout_name="settings_layout_version" layout_guid="40c0abb1-373a-4a51-b71c-e0425f2a16a1">
    <ChildGadgets>
      <NumericTextBox stylename="numeric_text_box" layout_id="major" layout_guid="2846c33b-e083-4b02-9e3e-a4796d92d0ec" left="162dpi_px" margin_left="2dpi_px" margin_right="2dpi_px" max="9999" input_type="Integer" />
      <NumericTextBox stylename="numeric_text_box" layout_id="minor" layout_guid="fe0435f3-2df5-4360-97a0-c8fa6f9d1d07" left="216dpi_px" margin_left="2dpi_px" margin_right="2dpi_px" max="9999" input_type="Integer" />
      <NumericTextBox stylename="numeric_text_box" layout_id="build" layout_guid="f01c673b-2037-4ced-ae2b-2cbded06d6eb" left="270dpi_px" margin_left="2dpi_px" margin_right="2dpi_px" max="9999" input_type="Integer" />
      <NumericTextBox stylename="numeric_text_box" layout_id="revision" layout_guid="4975b70b-ae1a-40f2-b3a8-02b4ec269031" left="324dpi_px" margin_left="2dpi_px" margin_right="2dpi_px" max="9999" input_type="Integer" />
      <Label stylename="label" layout_id="setting_label" layout_guid="f17fabcb-683c-4f6c-8844-32919f2785cc" height="16dpi_px" width="156dpi_px" left="2dpi_px" margin_left="2dpi_px" margin_right="2dpi_px" localise_caption="ggs_version" />
    </ChildGadgets>
  </Layout>
  <Layout layout_name="settings_layout_text_filtered" layout_guid="ead5811e-a098-4950-b03f-9429d5968729">
    <StackPanel stylename="settings_gadget_stack_panel">
      <Gadgets>
        <TextBox stylename="text_box" layout_id="setting_value" layout_guid="750b9bfa-0441-48f6-abf1-d784a0062962" width="200dpi_px" left="0dpi_px" margin_right="10dpi_px" />
        <Label stylename="settings_gadget_label" layout_id="setting_label" layout_guid="6edb7d43-2d4b-4539-a900-c6e47cfe0f4a" height="16dpi_px" width="0dpi_px" left="215dpi_px" margin_left="5dpi_px" />
      </Gadgets>
    </StackPanel>
  </Layout>
  <Layout layout_name="settings_layout_slider" layout_guid="7050928f-7b2b-4a7e-84da-5488d70600f0">
    <StackPanel stylename="settings_gadget_stack_panel" stack_order="TopToBottom">
      <Gadgets>
        <Label stylename="settings_gadget_label" layout_id="setting_label" layout_guid="381ecac8-72f6-484c-bf24-4790e003beb7" height="16px" width="0px" left="6dpi_px" top="0px" />
        <Slider stylename="settings_slider_grid" layout_id="setting_value" layout_guid="4ffabc4c-467d-4ec8-befa-54272d3c291e" width="160dpi_px" left="0px" top="20px" margin_top="4dpi_px" slider_style="settings_slider" thumb_style="settings_slider_thumb" slider_bar_style="settings_slider_bar" slider_bar_fill_style="settings_slider_bar_fill" slider_bar_fill_not_focused_style="settings_slider_bar_fill_not_focused" />
      </Gadgets>
    </StackPanel>
  </Layout>
  <Layout layout_name="settings_layout_box" layout_guid="f8900bd4-ac1b-4bee-926e-0280f990f619">
    <StackPanel stylename="settings_gadget_stack_panel">
      <Gadgets>
        <Label stylename="settings_gadget_label" layout_id="setting_label" />
        <Label stylename="settings_gadget_label" caption="BOX gadget TODO" />
      </Gadgets>
    </StackPanel>
  </Layout>
  <Layout layout_name="settings_layout_text_ip" layout_guid="763883a7-8d43-4985-8cde-459341a5eaa5">
    <StackPanel stylename="settings_gadget_stack_panel">
      <Gadgets>
        <TextBox stylename="text_box" layout_id="setting_value" layout_guid="a26c538d-8cc4-4fea-982b-5af56baae08a" width="200dpi_px" left="0dpi_px" margin_right="10dpi_px" />
        <Label stylename="settings_gadget_label" layout_id="setting_label" layout_guid="0f66e2b1-ab0a-4ace-8303-76ba26450a2d" height="16dpi_px" width="0dpi_px" left="215dpi_px" margin_left="5dpi_px" />
      </Gadgets>
    </StackPanel>
  </Layout>
  <Layout layout_name="gameoptions_addons" layout_guid="789184a8-8d29-492a-94b0-58791c632922">
    <ScrollPanel stylename="bordered_scrollpanel_dark" left="0px" top="0px" scrollpanel_flags="VerticalScroll">
      <ChildGadgets>
        <StackPanel stylename="stack_panel" layout_id="addons_panel" layout_guid="0cc7d0b8-1551-46d3-9b12-9b8f4dd324df" width="100%" left="0px" top="0px" stack_order="TopToBottom" stack_resize="ResizeHeight" />
      </ChildGadgets>
    </ScrollPanel>
  </Layout>
  <Layout layout_name="settings_layout_text_password" layout_guid="7c649167-358b-4f61-a414-260e5c0a584f">
    <StackPanel stylename="settings_gadget_stack_panel">
      <Gadgets>
        <StackPanel stylename="stack_panel" layout_id="setting_value" layout_guid="ed1ee81c-1534-4d39-af62-03591c8177ac" left="0px" stack_order="TopToBottom" stack_resize="ResizeAll">
          <ChildGadgets>
            <TextBox stylename="text_box" layout_id="password_box" layout_guid="a9e63399-dfed-474b-818b-97dadb743f15" width="200dpi_px" left="0px" top="0px" margin_right="10dpi_px" />
            <CheckBox stylename="checkbox_stack" layout_id="show_password" layout_guid="318034bc-e3a7-4094-ab64-c7919eb65d4d" localise_tooltip="Settings_ShowPassword" left="0dpi_px" top="24px" localise_name="Settings_ShowPassword" />
          </ChildGadgets>
        </StackPanel>
        <Label stylename="settings_gadget_label" layout_id="setting_label" layout_guid="0fdea64a-4db7-424c-ac21-563fd470890b" height="16px" width="0px" left="215px" margin_left="5dpi_px" />
      </Gadgets>
    </StackPanel>
  </Layout>
  <Layout layout_name="settings_layout_colour" layout_guid="136ed822-82e2-42e1-969a-4aa741576f67">
    <StackPanel stylename="settings_gadget_stack_panel">
      <Gadgets>
        <ColourSelectButton stylename="colour_select_button_up" layout_id="setting_value" layout_guid="020a26fd-be8b-484b-9b84-4cfbaabb2f13" left="0dpi_px" margin_right="10dpi_px" />
        <Label stylename="settings_gadget_label" layout_id="setting_label" layout_guid="0423c2d1-54f8-4352-a5b9-fd09fc4e66d9" height="16dpi_px" width="0dpi_px" left="35dpi_px" margin_left="5dpi_px" />
      </Gadgets>
    </StackPanel>
  </Layout>
  <Layout layout_name="settings_layout_boolean" layout_guid="1351dcef-a5c9-4e7b-bae2-dff11fcb7670">
    <CheckBox stylename="checkbox_stack" layout_id="setting_value" layout_guid="5c08702f-0683-4df1-b967-321d92aa6288" left="0dpi_dpi_px" />
  </Layout>
  <Layout layout_name="settings_layout_text_id" layout_guid="4cf368cb-d5d1-40cd-a370-cecf77449b2f">
    <StackPanel stylename="settings_gadget_stack_panel">
      <Gadgets>
        <TextBox stylename="text_box" layout_id="setting_value" layout_guid="5fb1e85c-5119-44e4-a881-ace2837f02b9" width="200dpi_px" left="0dpi_px" />
        <Label stylename="settings_gadget_label" layout_id="setting_label" layout_guid="f17d90c6-1a77-45be-8031-e3171f7d468e" height="16dpi_px" width="0dpi_px" left="200dpi_px" />
      </Gadgets>
    </StackPanel>
  </Layout>
  <Layout layout_name="settings_layout_eventlabel" layout_guid="8d1379aa-1506-4ffa-81c1-7bb5defcd619">
    <ChildGadgets>
      <Label stylename="label" layout_id="setting_label" layout_guid="02d7702f-881a-4534-8594-e44e33a9dda3" height="16px" width="340px" left="0px" top="0px" caption="Event label format (unchecked items are shown in the tooltip)" />
      <ListBox stylename="list_box" layout_id="listbox" allow_reorder="true" layout_guid="0fd4c61b-5ace-463a-975a-ee1a68d403e1" height="52dpi_px" width="200dpi_px" left="8px" top="20px" margin_top="4dpi_px">
        <ListBoxItems>
          <Grid stylename="grid_container" layout_id="description_grid" left="0%" top="0px" mouse_events="true" grid_rowlayout="['20dpi_px']" grid_columnlayout="['auto', '1*']" grid_resize="ResizeGridHeight">
            <Cell row="0" column="0" flow_index="0">
              <ChildGadgets>
                <Image stylename="image" mouse_events="false" height="12px" width="7px" left="4dpi_px" margin_right="8dpi_px" image="Buttons\widget_thumb.png" />
              </ChildGadgets>
            </Cell>
            <Cell row="0" column="1" flow_index="0">
              <ChildGadgets>
                <CheckBox stylename="checkbox_stack" layout_id="description_check" layout_guid="79a112aa-6699-4525-8205-576f0d98ce7e" left="0%" top="0px" localise_name="EventLabelFormat_Description" />
              </ChildGadgets>
            </Cell>
          </Grid>
          <Grid stylename="grid_container" layout_id="parent_grid" left="0%" top="20px" mouse_events="true" grid_rowlayout="['20dpi_px']" grid_columnlayout="['auto', '1*']" grid_resize="ResizeGridHeight">
            <Cell row="0" column="0" flow_index="0">
              <ChildGadgets>
                <Image stylename="image" mouse_events="false" height="12px" width="7px" left="4dpi_px" margin_right="8dpi_px" image="Buttons\widget_thumb.png" />
              </ChildGadgets>
            </Cell>
            <Cell row="0" column="1" flow_index="0">
              <ChildGadgets>
                <CheckBox stylename="checkbox_stack" layout_id="parent_check" layout_guid="030c5c43-1394-4a6f-bce3-3b01bc880c16" left="0%" top="0px" localise_name="EventLabelFormat_ParentObject" />
              </ChildGadgets>
            </Cell>
          </Grid>
        </ListBoxItems>
      </ListBox>
    </ChildGadgets>
  </Layout>
  <Layout layout_name="settings_layout_licence_gadget" layout_guid="4c8d6421-57f7-4596-b701-2f2832fb1301">
    <!--<StackPanel stylename="stack_panel"> -->
    <ChildGadgets>
      <CheckBox stylename="checkbox_stack" layout_id="accept_check" layout_guid="f390a95a-a485-42d3-8b17-933f1bcc5646" left="0px" localise_name="Spine_License_AcceptLabel" />
      <Button stylename="button_up" layout_id="show_button" layout_guid="a9ec4c12-1cdb-463b-8825-448dd413f850" width="120dpi_px" left="163px" margin_left="20dpi_px" localise_name="Spine_License_Show" />
    </ChildGadgets>
    <!--</StackPanel> -->
  </Layout>
</Layouts>
